{
	"group": "quantizedinformatics:draft",
    "type": "minecraft:crafting_shaped",
    "pattern": [
        "030",
        "415",
        "020"
    ],
    "key": {
        "0": {
            "item": "quantizedinformatics:quantum_fog"
        },
        "1": {
            "item": "quantizedinformatics:elem_si"
        },
        "2": {
            "item": "quantizedinformatics:draft_wire"
        },
        "3": {
            "item": "iron_ingot"
        },
        "4": {
            "item": "red_dye"
        },
        "5": {
            "item": "green_dye"
        }
    },
    "result": {
        "item": "quantizedinformatics:draft_listener"
    }
}
